Workbook

Sheet Summary
A1: Payments & Financial Services Jobs in India: Consulting, Product, Strategy, Growth
A3: • Compiled from web searches on 28 Sep 2026 (Google-style web search across company career sites, LinkedIn, Naukri, iimjobs, Instahyre, Foundit, Built In and other boards).
A4: • Direct page access to LinkedIn, Indeed and some career sites was blocked in the research environment, so the links were found through search but not opened one by one.
A5: • Postings on aggregators (BeBee, Jobaaj, The Muse, Built In, Workopia, GetMeReferred, Expertini) can be stale. Confirm each role is still open on the company's own careers page before applying.
A6: • 'Careers / search page' rows point to a company's job list or a filtered search where no single posting was found. Use them to find the current opening.
A7: • Yellow columns on the 'Job Openings' sheet are for you: track application status and notes there.
A10: Totals
A11: Companies | B11: =COUNTA(Companies!B:B)-1 -> 102
A12: Job links (rows) | B12: =COUNTA('Job Openings'!B:B)-1 -> 160
A13: Specific job postings | B13: =COUNTIF('Job Openings'!I:I,"Specific job posting") -> 122
A14: Careers / search pages | B14: =COUNTIF('Job Openings'!I:I,"Careers / search page") -> 38
A17: Company segment | B17: Companies | C17: Job links
A18: Consulting firm | B18: =COUNTIF(Companies!C:C,A18) -> 23 | C18: =COUNTIF('Job Openings'!C:C,A18) -> 33
A19: Payments fintech (India) | B19: =COUNTIF(Companies!C:C,A19) -> 27 | C19: =COUNTIF('Job Openings'!C:C,A19) -> 42
A20: Bank / card issuer | B20: =COUNTIF(Companies!C:C,A20) -> 24 | C20: =COUNTIF('Job Openings'!C:C,A20) -> 34
A21: Card network / payment system operator | B21: =COUNTIF(Companies!C:C,A21) -> 5 | C21: =COUNTIF('Job Openings'!C:C,A21) -> 13
A22: Cross-border payments | B22: =COUNTIF(Companies!C:C,A22) -> 6 | C22: =COUNTIF('Job Openings'!C:C,A22) -> 12
A23: Global payments & big tech | B23: =COUNTIF(Companies!C:C,A23) -> 5 | C23: =COUNTIF('Job Openings'!C:C,A23) -> 12
A24: Payments technology & processing | B24: =COUNTIF(Companies!C:C,A24) -> 12 | C24: =COUNTIF('Job Openings'!C:C,A24) -> 14
A25: Total | B25: =SUM(B18:B24) -> 102 | C25: =SUM(C18:C24) -> 160
A28: Role category | B28: Job links | C28: Share
A29: Consulting | B29: =COUNTIF('Job Openings'!E:E,A29) -> 24 | C29: =IF($B$12=0,0,B29/$B$12) -> 0.15
A30: Business Consulting | B30: =COUNTIF('Job Openings'!E:E,A30) -> 17 | C30: =IF($B$12=0,0,B30/$B$12) -> 0.10625
A31: Product Management | B31: =COUNTIF('Job Openings'!E:E,A31) -> 100 | C31: =IF($B$12=0,0,B31/$B$12) -> 0.625
A32: Strategy | B32: =COUNTIF('Job Openings'!E:E,A32) -> 7 | C32: =IF($B$12=0,0,B32/$B$12) -> 0.04375
A33: Growth | B33: =COUNTIF('Job Openings'!E:E,A33) -> 12 | C33: =IF($B$12=0,0,B33/$B$12) -> 0.075
A34: Other | B34: =COUNTIF('Job Openings'!E:E,A34) -> 0 | C34: =IF($B$12=0,0,B34/$B$12) -> 0

Sheet Companies
A1: # | B1: Company | C1: Segment | D1: Company type | E1: Job links found | F1: Role categories found | G1: Locations | H1: Best job link (first specific posting) | I1: Careers / all jobs page | J1: LinkedIn India job search | K1: Priority (you)
A2: 1 | B2: Razorpay | C2: Payments fintech (India) | D2: Payments fintech | E2: =COUNTIF('Job Openings'!B:B,B2) -> 2 | F2: Product Management | G2: Bengaluru | H2: https://in.linkedin.com/jobs/view/senior-product-manager-growth-at-razorpay-4416243265 | I2: https://razorpay.com/careers/ | J2: https://www.linkedin.com/jobs/search/?keywords=Razorpay&location=India
A3: 2 | B3: PhonePe | C3: Payments fintech (India) | D3: Payments fintech (UPI) | E3: =COUNTIF('Job Openings'!B:B,B3) -> 2 | F3: Product Management, Strategy | G3: Bengaluru | H3: https://in.linkedin.com/jobs/view/product-manager-at-phonepe-4397787803 | I3: https://www.phonepe.com/careers/job-openings/ | J3: https://www.linkedin.com/jobs/search/?keywords=PhonePe&location=India
A4: 3 | B4: Paytm | C4: Payments fintech (India) | D4: Payments fintech (UPI) | E4: =COUNTIF('Job Openings'!B:B,B4) -> 4 | F4: Product Management, Growth | G4: Noida / Bengaluru | H4: https://jobs.lever.co/paytm/64241793-684f-4dde-9447-36a14e499d4e | I4: https://jobs.lever.co/paytm | J4: https://www.linkedin.com/jobs/search/?keywords=Paytm&location=India
A5: 4 | B5: Cashfree Payments | C5: Payments fintech (India) | D5: Payment gateway | E5: =COUNTIF('Job Openings'!B:B,B5) -> 2 | F5: Product Management | G5: Bengaluru | H5: https://careers.kula.ai/cashfree/18060-product-manager-2 | I5: https://careers.kula.ai/cashfree | J5: https://www.linkedin.com/jobs/search/?keywords=Cashfree%20Payments&location=India
A6: 5 | B6: Juspay | C6: Payments fintech (India) | D6: Payments infrastructure | E6: =COUNTIF('Job Openings'!B:B,B6) -> 2 | F6: Product Management, Growth | G6: Bengaluru | H6: https://www.instahyre.com/job-74182-product-manager-apm-at-juspay-bangalore/ | I6: https://in.linkedin.com/jobs/juspay-jobs | J6: https://www.linkedin.com/jobs/search/?keywords=Juspay&location=India
A7: 6 | B7: PayU India | C7: Payments fintech (India) | D7: Payment gateway | E7: =COUNTIF('Job Openings'!B:B,B7) -> 2 | F7: Product Management | G7: Bengaluru / Gurugram | H7: https://careers.payu.in/PayU/job/Bengaluru-Product-Manager-Merchant-Management/3966280/ | I7: https://in.linkedin.com/jobs/payu-jobs | J7: https://www.linkedin.com/jobs/search/?keywords=PayU%20India&location=India
A8: 7 | B8: Pine Labs | C8: Payments fintech (India) | D8: Merchant payments / acquiring | E8: =COUNTIF('Job Openings'!B:B,B8) -> 1 | F8: Product Management | G8: Bengaluru / Noida | H8: https://www.instahyre.com/job-131077-product-manager-senior-product-manager-at-pine-labs-2-bangalore-noida/ | I8: https://www.pinelabs.com/careers/open-jobs | J8: https://www.linkedin.com/jobs/search/?keywords=Pine%20Labs&location=India
A9: 8 | B9: BharatPe | C9: Payments fintech (India) | D9: Merchant payments & lending | E9: =COUNTIF('Job Openings'!B:B,B9) -> 1 | F9: Product Management | G9: Gurugram / New Delhi | H9: https://jobs.insightpartners.com/companies/bharatpe-2/jobs/79697323-senior-product-manager | I9: https://in.linkedin.com/company/bharatpe/jobs | J9: https://www.linkedin.com/jobs/search/?keywords=BharatPe&location=India
A10: 9 | B10: MobiKwik | C10: Payments fintech (India) | D10: Wallet / consumer payments | E10: =COUNTIF('Job Openings'!B:B,B10) -> 2 | F10: Product Management, Growth | G10: Gurugram | H10: https://www.instahyre.com/job-116220-product-manager-at-mobikwik-2-gurgaon/ | I10: https://www.mobikwik.com/careers | J10: https://www.linkedin.com/jobs/search/?keywords=MobiKwik&location=India
A11: 10 | B11: CRED | C11: Payments fintech (India) | D11: Credit card payments / fintech | E11: =COUNTIF('Job Openings'!B:B,B11) -> 2 | F11: Product Management | G11: Bengaluru | H11: https://startup.jobs/product-manager-growth-cred_club-3005748 | I11: https://careers.cred.club/openings | J11: https://www.linkedin.com/jobs/search/?keywords=CRED&location=India
A12: 11 | B12: Zeta | C12: Payments technology & processing | D12: Card issuing / processing (Tachyon) | E12: =COUNTIF('Job Openings'!B:B,B12) -> 2 | F12: Product Management | G12: Bengaluru | H12: https://jobs.lever.co/zeta/8623c195-f912-4d87-952f-7114cd258413 | I12: https://jobs.lever.co/zeta | J12: https://www.linkedin.com/jobs/search/?keywords=Zeta&location=India
A13: 12 | B13: M2P Fintech | C13: Payments fintech (India) | D13: Card issuing / BaaS | E13: =COUNTIF('Job Openings'!B:B,B13) -> 2 | F13: Product Management | G13: Chennai / Bengaluru | H13: https://www.iimjobs.com/j/m-2-p-fintech-product-manager-3-6-yrs-1420797 | I13: https://careers.m2pfintech.com/ | J13: https://www.linkedin.com/jobs/search/?keywords=M2P%20Fintech&location=India
... A103: 102 | B103: Groww | C103: Payments fintech (India) | D103: Investing & payments fintech (UPI) | E103: =COUNTIF('Job Openings'!B:B,B103) -> 1 | F103: Product Management | G103: Bengaluru | H103: https://www.instahyre.com/job-414204-product-manager-at-groww-2-bangalore/ | I103: https://www.uplers.com/company/groww-8773 | J103: https://www.linkedin.com/jobs/search/?keywords=Groww&location=India

Sheet Job Openings
A1: # | B1: Company | C1: Segment | D1: Role / posting title | E1: Role category | F1: Role focus | G1: Location | H1: Job link | I1: Link type | J1: Found on | K1: Company careers / all jobs | L1: Before applying | M1: Application status (you) | N1: Notes (you)
A2: 1 | B2: Accenture Strategy & Consulting | C2: Consulting firm | D2: S&C - Financial Services Consultant/Manager (Banking) | E2: Consulting | F2: Consulting / Strategy | G2: India | H2: https://www.accenture.com/us-en/careers/jobdetails?id=R00284179_en | I2: Specific job posting | J2: Company careers (official) | K2: https://www.accenture.com/in-en/careers/explore-careers/area-of-interest/strategy-careers | L2: Confirm still open | M2: Not applied
A3: 2 | B3: Accenture Strategy & Consulting | C3: Consulting firm | D3: GN Banking - Trade Finance Consultant | E3: Business Consulting | F3: Business Consulting | G3: Gurugram / Mumbai / Bengaluru | H3: https://www.accenture.com/us-en/careers/jobdetails?id=R00305688_en | I3: Specific job posting | J3: Company careers (official) | K3: https://www.accenture.com/in-en/careers/explore-careers/area-of-interest/strategy-careers | L3: Confirm still open | M3: Not applied
A4: 3 | B4: Accenture Strategy & Consulting | C4: Consulting firm | D4: GN Banking - Data & AI Analyst | E4: Consulting | F4: Consulting / Analytics | G4: Delhi / Gurugram / Mumbai | H4: https://www.accenture.com/us-en/careers/jobdetails?id=R00305675_en | I4: Specific job posting | J4: Company careers (official) | K4: https://www.accenture.com/in-en/careers/explore-careers/area-of-interest/strategy-careers | L4: Confirm still open | M4: Not applied
A5: 4 | B5: Alvarez & Marsal | C5: Consulting firm | D5: Consulting roles in India (164 openings listed) | E5: Consulting | F5: Consulting | G5: Mumbai / Gurugram / Bengaluru | H5: https://careers.alvarezandmarsal.com/search/jobs/in/country/india | I5: Careers / search page | J5: Company careers (official) | K5: https://careers.alvarezandmarsal.com/ | L5: Confirm still open | M5: Not applied
A6: 5 | B6: Bain & Company | C6: Consulting firm | D6: Analyst - Financial Services (FS Centre of Expertise) | E6: Consulting | F6: Consulting / Research | G6: Gurugram | H6: https://www.bain.com/careers/find-a-role/position/?jobid=102140 | I6: Specific job posting | J6: Company careers (official) | K6: https://www.bain.com/careers/ | L6: Confirm still open | M6: Not applied
A7: 6 | B7: Bain & Company | C7: Consulting firm | D7: Associate - Financial Services (FS Centre of Expertise) | E7: Consulting | F7: Consulting / Research | G7: Gurugram | H7: https://www.bain.com/careers/find-a-role/position/?jobid=90399 | I7: Specific job posting | J7: Company careers (official) | K7: https://www.bain.com/careers/ | L7: Confirm still open | M7: Not applied
A8: 7 | B8: Boston Consulting Group (BCG) | C8: Consulting firm | D8: Consultant / Associate - Financial Institutions practice (India jobs page) | E8: Consulting | F8: Consulting / Strategy | G8: Mumbai / Gurugram / Bengaluru / Chennai / Hyderabad | H8: https://careers.bcg.com/global/en/locations/india | I8: Careers / search page | J8: Company careers (official) | K8: https://careers.bcg.com/global/en/locations/india | L8: Confirm still open | M8: Not applied
A9: 8 | B9: Capco | C9: Consulting firm | D9: Business Analyst - Payments domain | E9: Business Consulting | F9: Business Consulting | G9: Pune / Bengaluru | H9: https://job-boards.greenhouse.io/capco/jobs/7278632 | I9: Specific job posting | J9: Greenhouse (company ATS) | K9: https://job-boards.greenhouse.io/capco | L9: Confirm still open | M9: Not applied
A10: 9 | B10: Capgemini Invent | C10: Consulting firm | D10: Consulting roles (India careers) | E10: Business Consulting | F10: Business Consulting | G10: Mumbai / Bengaluru / Gurugram | H10: https://www.capgemini.com/in-en/careers/ | I10: Careers / search page | J10: Company careers (official) | K10: https://in.linkedin.com/company/capgemini/jobs | L10: Confirm still open | M10: Not applied
A11: 10 | B11: Cognizant | C11: Consulting firm | D11: Cards and Payments Business Analyst | E11: Business Consulting | F11: Business Consulting | G11: Chennai | H11: https://careers.cognizant.com/us-en/jobs/00066270001/cards-and-payments-business-analyst/ | I11: Specific job posting | J11: Company careers (official) | K11: https://careers.cognizant.com/india-en/ | L11: Confirm still open | M11: Not applied
A12: 11 | B12: Cognizant | C12: Consulting firm | D12: Consulting Analyst | E12: Business Consulting | F12: Business Consulting | G12: Chennai / Bengaluru / Pune | H12: https://careers.cognizant.com/india-en/jobs/00066859891/consulting-analyst/ | I12: Specific job posting | J12: Company careers (official) | K12: https://careers.cognizant.com/india-en/ | L12: Confirm still open | M12: Not applied
A13: 12 | B13: Deloitte India | C13: Consulting firm | D13: Consultant | Financial Services | Customer Strategy & Design | E13: Consulting | F13: Consulting / Strategy | G13: Mumbai | H13: https://southasiacareers.deloitte.com/job/Bengaluru-Consultant-Financial-Services-Mumbai-Customer-Strategy-&-Design/54711044 | I13: Specific job posting | J13: Company careers (official) | K13: https://southasiacareers.deloitte.com/ | L13: Confirm still open | M13: Not applied
... A161: 160 | B161: Zeta | C161: Payments technology & processing | D161: Associate Product Manager I/II - Tachyon | E161: Product Management | F161: Product Management | G161: Bengaluru | H161: https://startup.jobs/associate-product-manager-i-ii-tachyon-zeta-1818400 | I161: Specific job posting | J161: startup.jobs | K161: https://jobs.lever.co/zeta | L161: Confirm still open | M161: Not applied

Sheet Search Links
A1: Ready-made job searches (India) to refresh this list
A3: Search keywords | B3: LinkedIn (India) | C3: Naukri | D3: Indeed India
A4: payments product manager | B4: https://www.linkedin.com/jobs/search/?keywords=payments%20product%20manager&location=India | C4: https://www.naukri.com/payments-product-manager-jobs | D4: https://in.indeed.com/jobs?q=payments+product+manager&l=India
A5: payments strategy | B5: https://www.linkedin.com/jobs/search/?keywords=payments%20strategy&location=India | C5: https://www.naukri.com/payments-strategy-jobs | D5: https://in.indeed.com/jobs?q=payments+strategy&l=India
A6: financial services consultant | B6: https://www.linkedin.com/jobs/search/?keywords=financial%20services%20consultant&location=India | C6: https://www.naukri.com/financial-services-consultant-jobs | D6: https://in.indeed.com/jobs?q=financial+services+consultant&l=India
A7: cards product manager | B7: https://www.linkedin.com/jobs/search/?keywords=cards%20product%20manager&location=India | C7: https://www.naukri.com/cards-product-manager-jobs | D7: https://in.indeed.com/jobs?q=cards+product+manager&l=India
A8: UPI product manager | B8: https://www.linkedin.com/jobs/search/?keywords=UPI%20product%20manager&location=India | C8: https://www.naukri.com/upi-product-manager-jobs | D8: https://in.indeed.com/jobs?q=UPI+product+manager&l=India
A9: cross border payments | B9: https://www.linkedin.com/jobs/search/?keywords=cross%20border%20payments&location=India | C9: https://www.naukri.com/cross-border-payments-jobs | D9: https://in.indeed.com/jobs?q=cross+border+payments&l=India
A10: pricing strategy financial services | B10: https://www.linkedin.com/jobs/search/?keywords=pricing%20strategy%20financial%20services&location=India | C10: https://www.naukri.com/pricing-strategy-financial-services-jobs | D10: https://in.indeed.com/jobs?q=pricing+strategy+financial+services&l=India
A11: growth manager fintech | B11: https://www.linkedin.com/jobs/search/?keywords=growth%20manager%20fintech&location=India | C11: https://www.naukri.com/growth-manager-fintech-jobs | D11: https://in.indeed.com/jobs?q=growth+manager+fintech&l=India
A12: business consultant payments | B12: https://www.linkedin.com/jobs/search/?keywords=business%20consultant%20payments&location=India | C12: https://www.naukri.com/business-consultant-payments-jobs | D12: https://in.indeed.com/jobs?q=business+consultant+payments&l=India
A13: go to market fintech | B13: https://www.linkedin.com/jobs/search/?keywords=go%20to%20market%20fintech&location=India | C13: https://www.naukri.com/go-to-market-fintech-jobs | D13: https://in.indeed.com/jobs?q=go+to+market+fintech&l=India
A14: merchant acquiring | B14: https://www.linkedin.com/jobs/search/?keywords=merchant%20acquiring&location=India | C14: https://www.naukri.com/merchant-acquiring-jobs | D14: https://in.indeed.com/jobs?q=merchant+acquiring&l=India
A15: transaction banking product manager | B15: https://www.linkedin.com/jobs/search/?keywords=transaction%20banking%20product%20manager&location=India | C15: https://www.naukri.com/transaction-banking-product-manager-jobs | D15: https://in.indeed.com/jobs?q=transaction+banking+product+manager&l=India
